mlflow_knative/__init__.py
mlflow_knative/deployment_client.py
mlflow_knative/knative.py
mlflow_knative/mlflow_docker.py
mlflow_knative/service.yaml
mlflow_knative/templating.py
mlflow_knative-0.4.3.dist-info/LICENSE.md
mlflow_knative-0.4.3.dist-info/METADATA
mlflow_knative-0.4.3.dist-info/WHEEL
mlflow_knative-0.4.3.dist-info/entry_points.txt
mlflow_knative-0.4.3.dist-info/RECORD
