Metadata-Version: 2.1
Name: mlflow-knative
Version: 0.4.3
Summary: MLflow plugin adding a Knative deployment target
Home-page: https://gitlab.com/lzinsou/mlflow-knative
Keywords: mlflow,plugin,mlops,deployment,deployments,knative,kubernetes,kn,k8s
Author: Loris Zinsou
Author-email: lzinsou@protonmail.com
Requires-Python: >=3.10,<3.13
Classifier: Development Status :: 4 - Beta
Classifier: Environment :: Plugins
Classifier: Programming Language :: Python :: 3
Classifier: Programming Language :: Python :: 3.10
Classifier: Programming Language :: Python :: 3.11
Requires-Dist: docker (>=6.1.3,<7.0.0)
Requires-Dist: kubernetes (>=26.1.0,<27.0.0)
Requires-Dist: pyyaml (>=6.0,<7.0)
Requires-Dist: types-pyyaml (>=6.0.12.10,<7.0.0.0)
Project-URL: Repository, https://gitlab.com/lzinsou/mlflow-knative
